{
	"date":[
		{
			"qi":"5",
			"zhi":"7",
			"str":"清晨",
			"wenhou":["起床这么早，锻炼一下吧^v^",
				"补漏趁天晴，读书趁年轻。",
				"实施成果要展现，持之以恒是关键。"]
		},
		{
			"qi":"7",
			"zhi":"9",
			"str":"早上",
			"wenhou":["黄河远上白云间，一片孤城万仞山。",
				"总有一天我要让我的名字成为你们口中的骄傲。",
				"大肚能容，断却许多烦恼障，笑容可掬，结成无量欢喜缘。"]
		},
		{
			"qi":"9",
			"zhi":"12",
			"str":"上午",
			"wenhou":["微笑，是强者对人生最完美的诠释；微笑，是从从容容的人生态度。",
				"激情是生活中一种永远向上的力量。激情面对生活，微笑面对自己！",
				"爱情很美好，相信爱情。如果连爱情都不相信那人生岂不太苦了"]
		},
		{
			"qi":"12",
			"zhi":"14",
			"str":"中午",
			"wenhou":["没有任何语言能够表达的时候，就让沉默来代替语言发出该有的声音。",
				"如果你看到了面前的阴影，请不要害怕，那是因为你的背后还有阳光。",
				"你给的世界，满满的都是爱。"]
		},
		{
			"qi":"14",
			"zhi":"18",
			"str":"下午",
			"wenhou":["幸福是就是找一个温暖的人过一辈子。",
				"嘴甜是因为心甜 心甜是因为里面有你",
				"你有地图吗，我在你的眼睛里迷路了。"]
		},
		{
			"qi":"18",
			"zhi":"19",
			"str":"傍晚",
			"wenhou":["世上最幸福的工作就是做你的专职爱人。",
				"我觉得你接近我是为了害我 害得我好喜欢你呀",
				"真正的爱情是，我让你动了心，你让我安了心。"]
		},
		{
			"qi":"19",
			"zhi":"0",
			"str":"晚上",
			"wenhou":["从今往后让我们一起走，细腻的心思我们一起拥有。",
				"梦里有你，香甜无比;心里有你，充实无比;身边有你，幸福无比。",
				"不乱于心，不困于情。不畏将来，不念过往。"]
		},
		{
			"qi":"0",
			"zhi":"5",
			"str":"凌晨",
			"wenhou":["人不快乐的原因就是把自己关在一个跑不掉的地方。",
				"人只要生活在这个世界上，就会有很多烦恼。但是，痛苦和快乐取决于你的内心。",
				"太容易的路，可能根本不能带你去任何地方。"]
		}
	]

}